remote_user_authenticator/__init__.py
remote_user_authenticator/remote_user_authenticator.py
jupyterhub_remote_user_authenticator-1.0.0.dist-info/LICENCE
jupyterhub_remote_user_authenticator-1.0.0.dist-info/METADATA
jupyterhub_remote_user_authenticator-1.0.0.dist-info/WHEEL
jupyterhub_remote_user_authenticator-1.0.0.dist-info/top_level.txt
jupyterhub_remote_user_authenticator-1.0.0.dist-info/RECORD
