Metadata-Version: 2.1
Name: jupyterhub-remote-user-authenticator
Version: 1.0.0
Summary: Remote User Authenticator for JupyterHub
Home-page: https://github.com/izihawa/remote_user_authenticator
Author: ppodolsky
Author-email: ppodolsky@me.com
License: Apache 2.0
Platform: UNKNOWN
Requires-Dist: jupyterhub
